kd_ar_stream/__init__.py
kd_ar_stream/core.py
kd_ar_stream/utils.py
kd_ar_stream/data/ExclaStar.txt
kd_ar_stream-1.0.8.dist-info/licenses/LICENSE
kd_ar_stream-1.0.8.dist-info/METADATA
kd_ar_stream-1.0.8.dist-info/WHEEL
kd_ar_stream-1.0.8.dist-info/top_level.txt
kd_ar_stream-1.0.8.dist-info/RECORD
