Metadata-Version: 2.4
Name: kd-ar-stream
Version: 1.0.8
Summary: KD-AR Stream: Real-Time Data Stream Clustering with Adaptive Radius
Home-page: https://github.com/senolali/kd-ar-stream
Author: Ali Şenol
Author-email: alisenol@tarsus.edu.tr
License: MIT
Project-URL: Homepage, https://github.com/senolali/kd-ar-stream
Project-URL: Documentation, https://github.com/senolali/kd-ar-stream
Project-URL: Source, https://github.com/senolali/kd-ar-stream
Project-URL: Issues, https://github.com/senolali/kd-ar-stream
Project-URL: Paper, https://doi.org/10.17341/gazimmfd.467226
Classifier: Programming Language :: Python :: 3
Classifier: License :: OSI Approved :: MIT License
Classifier: Operating System :: OS Independent
Requires-Python: >=3.10
License-File: LICENSE
Requires-Dist: numpy>=1.24.0
Requires-Dist: scipy>=1.11.0
Requires-Dist: matplotlib>=3.7.0
Dynamic: author
Dynamic: author-email
Dynamic: classifier
Dynamic: description
Dynamic: description-content-type
Dynamic: home-page
Dynamic: license
Dynamic: license-file
Dynamic: project-url
Dynamic: requires-dist
Dynamic: requires-python
Dynamic: summary
